phishscan/__init__.py
phishscan/cli.py
phishscan/email_processor.py
phishscan/phishing_detector.py
phishscan-1.0.4.dist-info/licenses/LICENSE
phishscan-1.0.4.dist-info/METADATA
phishscan-1.0.4.dist-info/WHEEL
phishscan-1.0.4.dist-info/entry_points.txt
phishscan-1.0.4.dist-info/top_level.txt
phishscan-1.0.4.dist-info/RECORD
